py3dep/__init__.py
py3dep/cli.py
py3dep/exceptions.py
py3dep/geoops.py
py3dep/print_versions.py
py3dep/py.typed
py3dep/py3dep.py
py3dep-0.19.0.dist-info/METADATA
py3dep-0.19.0.dist-info/WHEEL
py3dep-0.19.0.dist-info/entry_points.txt
py3dep-0.19.0.dist-info/licenses/AUTHORS.rst
py3dep-0.19.0.dist-info/licenses/LICENSE
py3dep-0.19.0.dist-info/RECORD
