Metadata-Version: 2.4
Name: py3dep
Version: 0.19.0
Summary: Access topography data at any resolution via 3DEP web service of USGS.
Project-URL: Changelog, https://docs.hyriver.io/changelogs/py3dep.html
Project-URL: CI, https://github.com/hyriver/py3dep/actions
Project-URL: Homepage, https://docs.hyriver.io/readme/py3dep.html
Project-URL: Issues, https://github.com/hyriver/py3dep/issues
Author-email: Taher Chegini <cheginit@gmail.com>
License: MIT
License-File: AUTHORS.rst
License-File: LICENSE
Classifier: Development Status :: 4 - Beta
Classifier: Intended Audience :: Science/Research
Classifier: License :: OSI Approved :: MIT License
Classifier: Operating System :: OS Independent
Classifier: Programming Language :: Python
Classifier: Programming Language :: Python :: 3 :: Only
Classifier: Programming Language :: Python :: 3.9
Classifier: Programming Language :: Python :: 3.10
Classifier: Programming Language :: Python :: 3.11
Classifier: Programming Language :: Python :: 3.12
Classifier: Programming Language :: Python :: 3.13
Classifier: Topic :: Scientific/Engineering
Classifier: Topic :: Scientific/Engineering :: GIS
Classifier: Topic :: Scientific/Engineering :: Hydrology
Classifier: Typing :: Typed
Requires-Python: >=3.9
Requires-Dist: async-retriever<0.20,>=0.19
Requires-Dist: click>=0.7
Requires-Dist: cytoolz
Requires-Dist: geopandas>=1
Requires-Dist: numpy>=1.17
Requires-Dist: pygeoogc<0.20,>=0.19
Requires-Dist: pygeoutils<0.20,>=0.19
Requires-Dist: rasterio>=1.2
Requires-Dist: rioxarray>=0.11
Requires-Dist: shapely>=2
Requires-Dist: xarray>=2023.1
Provides-Extra: jit
Requires-Dist: numba>=0.60; extra == 'jit'
Provides-Extra: test
Requires-Dist: pytest-cov; extra == 'test'
Requires-Dist: pytest-sugar; extra == 'test'
